pelican/plugins/pybtex/__init__.py
pelican/plugins/pybtex/generator.py
pelican/plugins/pybtex/injector.py
pelican/plugins/pybtex/signals.py
pelican/plugins/pybtex/style.py
pelican/plugins/pybtex/utils.py
pelican/plugins/pybtex/templates/bibliography.html
pelican/plugins/pybtex/templates/publications.html
pelican_pybtex-1.0.1.dist-info/METADATA
pelican_pybtex-1.0.1.dist-info/WHEEL
pelican_pybtex-1.0.1.dist-info/RECORD
