Metadata-Version: 2.3
Name: pelican-pybtex
Version: 1.0.1
Summary: Manage your academic publications page with Pelican and pybtex (BibTeX)
Project-URL: Homepage, https://github.com/anjos/pelican-pybtex
Project-URL: Issue Tracker, https://github.com/anjos/pelican-pybtex/issues
Author-email: Andre Anjos <andre.dos.anjos@gmail.com>
License-Expression: MIT
Keywords: bibtex,pelican,plugin,pybtex
Classifier: Development Status :: 5 - Production/Stable
Classifier: Environment :: Console
Classifier: Framework :: Pelican
Classifier: Framework :: Pelican :: Plugins
Classifier: Intended Audience :: End Users/Desktop
Classifier: License :: OSI Approved :: MIT License
Classifier: Operating System :: OS Independent
Classifier: Programming Language :: Python :: 3
Classifier: Programming Language :: Python :: 3.9
Classifier: Programming Language :: Python :: 3.10
Classifier: Programming Language :: Python :: 3.11
Classifier: Programming Language :: Python :: 3.12
Classifier: Programming Language :: Python :: 3.13
Classifier: Topic :: Internet :: WWW/HTTP
Classifier: Topic :: Software Development :: Libraries :: Python Modules
Requires-Python: <4.0,>=3.9
Requires-Dist: pelican>=4.5
Requires-Dist: pybtex
Requires-Dist: pygments>=2.2
Provides-Extra: qa
Requires-Dist: pre-commit; extra == 'qa'
Provides-Extra: test
Requires-Dist: beautifulsoup4; extra == 'test'
Requires-Dist: markdown; extra == 'test'
Requires-Dist: pytest; extra == 'test'
Requires-Dist: pytest-cov; extra == 'test'
